graphql_http_server/__init__.py
graphql_http_server/error.py
graphql_http_server/helpers.py
graphql_http_server/server.py
graphql_http_server/graphiql/index.html
graphql_http_server-1.6.1.dist-info/licenses/LICENSE
tests/__init__.py
tests/app.py
tests/app_federation.py
tests/conftest.py
tests/test_federation.py
tests/test_graphql_api.py
graphql_http_server-1.6.1.dist-info/METADATA
graphql_http_server-1.6.1.dist-info/WHEEL
graphql_http_server-1.6.1.dist-info/top_level.txt
graphql_http_server-1.6.1.dist-info/RECORD
